zidauth/__init__.py
zidauth/admin.py
zidauth/apps.py
zidauth/consts.py
zidauth/models.py
zidauth/tests.py
zidauth/urls.py
zidauth/views.py
zidauth/views.test.py
zidauth/migrations/0001_initial.py
zidauth/migrations/__init__.py
zidauth-0.1.dist-info/LICENSE
zidauth-0.1.dist-info/METADATA
zidauth-0.1.dist-info/WHEEL
zidauth-0.1.dist-info/top_level.txt
zidauth-0.1.dist-info/RECORD
