Metadata-Version: 2.1
Name: zidauth
Version: 0.1
Summary: boilerplate for your custom zid App Market application that provides basic oauth functionality 
License: MIT License
Project-URL: Repository, https://bitbucket.org/takizee/zidauth
Requires-Python: >=3.12.0
License-File: LICENSE
Requires-Dist: Django>=5.1.3
Requires-Dist: requests>=2.32.3
